wotconsole/__init__.py
wotconsole/api.py
wotconsole/session.py
wotconsole/utils.py
wotconsole-0.4.2.dist-info/DESCRIPTION.rst
wotconsole-0.4.2.dist-info/METADATA
wotconsole-0.4.2.dist-info/RECORD
wotconsole-0.4.2.dist-info/WHEEL
wotconsole-0.4.2.dist-info/metadata.json
wotconsole-0.4.2.dist-info/top_level.txt
