Metadata-Version: 2.0
Name: wotconsole
Version: 0.4.2
Summary: WarGaming World of Tanks Console API Wrapper
Home-page: https://bitbucket.org/kamakazikamikaze/wotconsole
Author: Kent Coble
Author-email: coblekent@gmail.com
License: LICENSE.TXT
Platform: UNKNOWN
Requires-Dist: requests (>=2.22.0)
